MANIFEST.in
setup.py
cheese_freezer/__init__.py
cheese_freezer.egg-info/PKG-INFO
cheese_freezer.egg-info/SOURCES.txt
cheese_freezer.egg-info/dependency_links.txt
cheese_freezer.egg-info/entry_points.txt
cheese_freezer.egg-info/top_level.txt