Metadata-Version: 1.0
Name: cheese-freezer
Version: 0.0.3
Summary: Upload helper for your local PyPI mirror
Home-page: http://github.com/lqc/cheese-freezer/
Author: Łukasz Rekucki
Author-email: lrekucki@gmail.com
License: BSD
Keywords: pypi chishop upload mirror
Platform: UNKNOWN
Classifier: Development Status :: 3 - Alpha
Classifier: Environment :: Console
Classifier: Topic :: Utilities
Classifier: License :: OSI Approved :: BSD License
Classifier: Programming Language :: Python :: 2.6
Classifier: Programming Language :: Python :: 2.7
